{"proxyEnv":"pleasant-compassion-production.up.railway.app","enabled":true,"team1":{"query":"Natus Vincere","found":{"teamId":4608,"slug":"natus-vincere","name":"Natus Vincere"}},"team2":{"query":"FaZe","found":{"teamId":6667,"slug":"faze","name":"FaZe"}},"matchInfo":{"matchId":2393321,"live":false,"url":"https://www.hltv.org/matches/2393321/natus-vincere-vs-faze-blast-rivals-2026-season-1","event":null},"enrichSummary":{"form1":{"wins":8,"losses":2,"winRate":80,"recent":["W","W","L","W","L","W","W","W","W","W"],"streak":2},"form2":{"wins":5,"losses":5,"winRate":50,"recent":["L","L","W","W","W","W","L","L","W","L"],"streak":-2},"h2h":{"t1Wins":0,"t2Wins":0,"totalMatches":0}},"scoreboardSummary":null}