{
  "version": 1,
  "game": "mma",
  "fittedAt": "2026-05-13T18:25:23.366Z",
  "method": "isotonic_pav",
  "nCalibSamples": 473,
  "blocks": [
    {
      "pMin": 0.3547,
      "pMax": 0.45,
      "yMean": 0.42,
      "n": 100
    },
    {
      "pMin": 0.4512,
      "pMax": 0.4995,
      "yMean": 0.4603,
      "n": 126
    },
    {
      "pMin": 0.5001,
      "pMax": 0.5998,
      "yMean": 0.5343,
      "n": 204
    },
    {
      "pMin": 0.603,
      "pMax": 0.6462,
      "yMean": 0.5667,
      "n": 30
    },
    {
      "pMin": 0.6505,
      "pMax": 0.6926,
      "yMean": 0.6667,
      "n": 9
    }
  ],
  "trainingNote": "Walk-forward surface-agnostic Elo; aplicar pós-trained model output."
}